jpl.labcas.downloader-0.1.1-py3.11-nspkg.pth
jpl/labcas/downloader/VERSION.txt
jpl/labcas/downloader/__init__.py
jpl/labcas/downloader/_download.py
jpl/labcas/downloader/main.py
jpl.labcas.downloader-0.1.1.dist-info/LICENSE.md
jpl.labcas.downloader-0.1.1.dist-info/METADATA
jpl.labcas.downloader-0.1.1.dist-info/NOTICE.txt
jpl.labcas.downloader-0.1.1.dist-info/WHEEL
jpl.labcas.downloader-0.1.1.dist-info/entry_points.txt
jpl.labcas.downloader-0.1.1.dist-info/namespace_packages.txt
jpl.labcas.downloader-0.1.1.dist-info/top_level.txt
jpl.labcas.downloader-0.1.1.dist-info/zip-safe
jpl.labcas.downloader-0.1.1.dist-info/RECORD
