Metadata-Version: 2.1
Name: jpl.labcas.downloader
Version: 0.1.1
Summary: A simple Python package to download files from LabCAS
Home-page: https://github.com/EDRN/labcas-downloader
Download-URL: https://github.com/EDRN/labcas-downloader/releases/
Author: Asitang Mishra
Author-email: asitang.mishra@jpl.nasa.gov
Maintainer: Sean Kelly
Maintainer-email: sean.kelly@jpl.nasa.gov
License: apache-2.0
Keywords: laboratory,data,labcas,downloader,automation
Classifier: Programming Language :: Python :: 3
Classifier: License :: OSI Approved :: Apache Software License
Classifier: Operating System :: OS Independent
Requires-Python: >=3.8
License-File: LICENSE.md
License-File: NOTICE.txt
Requires-Dist: requests==2.26.0
Provides-Extra: dev
Requires-Dist: wheel; extra == "dev"
Requires-Dist: build; extra == "dev"
